fast_installer/__init__.py
fast_installer/install.py
fast_installer/methods/__init__.py
fast_installer/methods/link.py
fast_installer/methods/shell.py
fast_installer/methods/utils.py
fast_installer-1.2.0.dist-info/METADATA
fast_installer-1.2.0.dist-info/WHEEL
fast_installer-1.2.0.dist-info/entry_points.txt
fast_installer-1.2.0.dist-info/top_level.txt
fast_installer-1.2.0.dist-info/RECORD
