Metadata-Version: 2.1
Name: fast-installer
Version: 1.2.0
Summary: fast pythonic installer for projects using yaml config
Home-page: https://github.com/IamShobe/fast-installer
Author: Elran Shefer
License: UNKNOWN
Keywords: fast installer
Platform: UNKNOWN
Requires-Dist: docopt
Requires-Dist: pyyaml
Requires-Dist: attrdict
Requires-Dist: inquirer
